MarkovText/MarkovText.py
MarkovText/__init__.py
MarkovText-0.1.dev7.dist-info/DESCRIPTION.rst
MarkovText-0.1.dev7.dist-info/METADATA
MarkovText-0.1.dev7.dist-info/RECORD
MarkovText-0.1.dev7.dist-info/WHEEL
MarkovText-0.1.dev7.dist-info/metadata.json
MarkovText-0.1.dev7.dist-info/top_level.txt
