Metadata-Version: 2.0
Name: MarkovText
Version: 0.1.dev7
Summary: A package to generate text via Markov chain using sample text
Home-page: https://github.com/kwkelly/MarkovText
Author: Keith Kelly
Author-email: k3ithk@gmail.com
License: MIT
Keywords: markov chain text generator
Platform: UNKNOWN
Classifier: Development Status :: 3 - Alpha
Classifier: Intended Audience :: Developers
Classifier: Topic :: Software Development :: Build Tools
Classifier: License :: OSI Approved :: MIT License
Classifier: Programming Language :: Python :: 2
Classifier: Programming Language :: Python :: 2.6
Classifier: Programming Language :: Python :: 2.7
Classifier: Programming Language :: Python :: 3
Classifier: Programming Language :: Python :: 3.3
Classifier: Programming Language :: Python :: 3.4
Classifier: Programming Language :: Python :: 3.5
Requires-Dist: numpy
